smap/__init__.py
smap/rectify.py
smap/smap.py
smap/specials.py
smap/utils.py
smap_torch-1.0.4.dist-info/licenses/LICENSE
tools/__init__.py
tools/testing/__init__.py
tools/testing/vtest/__init__.py
tools/testing/vtest/vtest_types.py
smap_torch-1.0.4.dist-info/METADATA
smap_torch-1.0.4.dist-info/WHEEL
smap_torch-1.0.4.dist-info/top_level.txt
smap_torch-1.0.4.dist-info/RECORD
