Metadata-Version: 2.4
Name: smap-torch
Version: 1.0.4
Summary: An open source pytorch library for spatial mapping based on 2D representations
Home-page: https://github.com/thienannguyen-cv/SMap
Author: Thien An L. Nguyen
Author-email: thienannguyen.cv@gmail.com
License: Apache-2.0
Classifier: Programming Language :: Python :: 3
Classifier: License :: OSI Approved :: Apache Software License
Classifier: Operating System :: OS Independent
Requires-Python: >=3.6.7
License-File: LICENSE
Requires-Dist: torch>=1.3.1
Requires-Dist: numpy>=1.19.5
Dynamic: author
Dynamic: author-email
Dynamic: classifier
Dynamic: description
Dynamic: description-content-type
Dynamic: home-page
Dynamic: license
Dynamic: license-file
Dynamic: requires-dist
Dynamic: requires-python
Dynamic: summary
